MANIFEST.in
README.md
setup.py
clefairy.egg-info/PKG-INFO
clefairy.egg-info/SOURCES.txt
clefairy.egg-info/dependency_links.txt
clefairy.egg-info/entry_points.txt
clefairy.egg-info/not-zip-safe
clefairy.egg-info/top_level.txt
pokemon/__init__.py
pokemon/convert.py
pokemon/make_db.py
pokemon/master.py
pokemon/scripts.py
pokemon/skills.py
pokemon/utils.py
pokemon/database/pokemons.json
pokemon/database/images/1.jpg
pokemon/database/images/10.jpg
pokemon/database/images/100.jpg
pokemon/database/images/101.jpg
pokemon/database/images/102.jpg
pokemon/database/images/103.jpg
pokemon/database/images/104.jpg
pokemon/database/images/105.jpg
pokemon/database/images/106.jpg
pokemon/database/images/107.jpg
pokemon/database/images/108.jpg
pokemon/database/images/109.jpg
pokemon/database/images/11.jpg
pokemon/database/images/110.jpg
pokemon/database/images/111.jpg
pokemon/database/images/112.jpg
pokemon/database/images/113.jpg
pokemon/database/images/114.jpg
pokemon/database/images/115.jpg
pokemon/database/images/116.jpg
pokemon/database/images/117.jpg
pokemon/database/images/118.jpg
pokemon/database/images/119.jpg
pokemon/database/images/12.jpg
pokemon/database/images/120.jpg
pokemon/database/images/121.jpg
pokemon/database/images/122.jpg
pokemon/database/images/123.jpg
pokemon/database/images/124.jpg
pokemon/database/images/125.jpg
pokemon/database/images/126.jpg
pokemon/database/images/127.jpg
pokemon/database/images/128.jpg
pokemon/database/images/129.jpg
pokemon/database/images/13.jpg
pokemon/database/images/130.jpg
pokemon/database/images/131.jpg
pokemon/database/images/132.jpg
pokemon/database/images/133.jpg
pokemon/database/images/134.jpg
pokemon/database/images/135.jpg
pokemon/database/images/136.jpg
pokemon/database/images/137.jpg
pokemon/database/images/138.jpg
pokemon/database/images/139.jpg
pokemon/database/images/14.jpg
pokemon/database/images/140.jpg
pokemon/database/images/141.jpg
pokemon/database/images/142.jpg
pokemon/database/images/143.jpg
pokemon/database/images/144.jpg
pokemon/database/images/145.jpg
pokemon/database/images/146.jpg
pokemon/database/images/147.jpg
pokemon/database/images/148.jpg
pokemon/database/images/149.jpg
