Metadata-Version: 1.0
Name: clefairy
Version: 0.100
Summary: ascii database of pokemon... in python!
Home-page: http://www.github.com/vsoch/pokemon
Author: Vanessa Sochat
Author-email: vsochat@stanford.edu
License: LICENSE
Keywords: pokemon,avatar,ascii,gravatar
Platform: UNKNOWN
